pyoda_time/__init__.py
pyoda_time/_ambiguous_time_error.py
pyoda_time/_annual_date.py
pyoda_time/_calendar_ordinal.py
pyoda_time/_calendar_system.py
pyoda_time/_date_adjusters.py
pyoda_time/_date_interval.py
pyoda_time/_date_time_zone.py
pyoda_time/_date_time_zone_providers.py
pyoda_time/_duration.py
pyoda_time/_i_clock.py
pyoda_time/_i_date_time_zone_provider.py
pyoda_time/_instant.py
pyoda_time/_interval.py
pyoda_time/_iso_day_of_week.py
pyoda_time/_local_date.py
pyoda_time/_local_date_time.py
pyoda_time/_local_instant.py
pyoda_time/_local_time.py
pyoda_time/_offset.py
pyoda_time/_offset_date_time.py
pyoda_time/_offset_time.py
pyoda_time/_period.py
pyoda_time/_period_builder.py
pyoda_time/_period_units.py
pyoda_time/_pyoda_constants.py
pyoda_time/_skipped_time_error.py
pyoda_time/_system_clock.py
pyoda_time/_time_adjusters.py
pyoda_time/_year_month.py
pyoda_time/_year_month_day.py
pyoda_time/_year_month_day_calendar.py
pyoda_time/_zoned_clock.py
pyoda_time/_zoned_date_time.py
pyoda_time/py.typed
pyoda_time/_compatibility/__init__.py
pyoda_time/_compatibility/_argument_exception.py
pyoda_time/_compatibility/_calendar.py
pyoda_time/_compatibility/_calendar_data.py
pyoda_time/_compatibility/_calendar_id.py
pyoda_time/_compatibility/_culture_data.py
pyoda_time/_compatibility/_culture_info.py
pyoda_time/_compatibility/_culture_not_found_exception.py
pyoda_time/_compatibility/_culture_types.py
pyoda_time/_compatibility/_date_time_format_info.py
pyoda_time/_compatibility/_day_of_week.py
pyoda_time/_compatibility/_globalization_mode.py
pyoda_time/_compatibility/_gregorian_calendar.py
pyoda_time/_compatibility/_gregorian_calendar_helper.py
pyoda_time/_compatibility/_gregorian_calendar_types.py
pyoda_time/_compatibility/_hebrew_calendar.py
pyoda_time/_compatibility/_hijri_calendar.py
pyoda_time/_compatibility/_i_format_provider.py
pyoda_time/_compatibility/_icu_locale_data.py
pyoda_time/_compatibility/_interop.py
pyoda_time/_compatibility/_japanese_calendar.py
pyoda_time-0.10.0.dist-info/METADATA
pyoda_time-0.10.0.dist-info/WHEEL
pyoda_time-0.10.0.dist-info/licenses/LICENSE.txt
pyoda_time-0.10.0.dist-info/licenses/NOTICE.txt
pyoda_time-0.10.0.dist-info/RECORD
