Metadata-Version: 2.4
Name: pyoda-time
Version: 0.10.0
Summary: An alternative datetime library for Python.
Project-URL: Homepage, https://pyodatime.org/
Project-URL: Repository, https://github.com/chrisimcevoy/pyoda-time
Project-URL: Changelog, https://github.com/chrisimcevoy/pyoda-time/blob/main/CHANGELOG.md
Author-email: Chris McEvoy <chris@chrismcevoy.net>
License: Apache-2.0
License-File: LICENSE.txt
License-File: NOTICE.txt
Classifier: Development Status :: 3 - Alpha
Classifier: Intended Audience :: Developers
Classifier: License :: OSI Approved :: Apache Software License
Classifier: Programming Language :: Python :: 3.12
Classifier: Programming Language :: Python :: 3.13
Classifier: Typing :: Typed
Requires-Python: >=3.12
Requires-Dist: pyicu>=2.14
